jorgesomasfinal/__init__.py
jorgesomasfinal/soma.py
jorgesomasfinal-0.1.dist-info/LICENSE
jorgesomasfinal-0.1.dist-info/METADATA
jorgesomasfinal-0.1.dist-info/WHEEL
jorgesomasfinal-0.1.dist-info/top_level.txt
jorgesomasfinal-0.1.dist-info/RECORD
